file-traversal/__init__.py
file-traversal/filetraversal.py
file-traversal/filetraversalresult.py
file_traversal/__init__.py
file_traversal/filetraversal.py
file_traversal/filetraversalresult.py
tests/__init__.py
tests/filetraversal_test.py
file_traversal-0.1.3.dist-info/METADATA
file_traversal-0.1.3.dist-info/WHEEL
file_traversal-0.1.3.dist-info/top_level.txt
file_traversal-0.1.3.dist-info/RECORD
